{
	"ident": 1027,
	"order": 27,
	"objtype": "kComponent",
	"componentlib": "jsDgrd",
	"componentctrl": "Data grid Control",
	"properties": {
		"::boldheader": false,
		"::candragdisplayorder": false,
		"::columnwidths": "100,371,74,80,100",
		"::headerheight": 0,
		"::rowheight": 0,
		"alpha": 255,
		"autocapitalize": "kJSAutoCapitalizeSentences",
		"autocorrect": true,
		"autoedit": false,
		"backalpha": 255,
		"backcolor": "RGB(255,255,255)",
		"bordercolor": "kColorDefault",
		"canresizecolumns": true,
		"cansortcolumns": true,
		"columnnames": "Conference,Title,attended,maximum,percent",
		"columnwidthsarepercentage": false,
		"contextmenu": "rmcSpeaker",
		"cssclassname": "",
		"dataname": "ilPastTopics",
		"dateformat": "kJSFormatNone",
		"dateformatcustom": "",
		"desgroup": 0,
		"designactive": true,
		"designcols": 5,
		"deslock": false,
		"disabledefaultcontextmenu": false,
		"disablesystemfocus": false,
		"dragmode": "kNoDragging",
		"dropmode": "kAcceptNone",
		"effect": "kJSborderPlain",
		"enabled": true,
		"enterable": false,
		"evenrowcolor": "kColorDefault",
		"events": "evExecuteContextMenu,evClick",
		"extendable": false,
		"fieldstyle": "",
		"filterareaheight": 0,
		"filtercol": 0,
		"filterlabel": "",
		"filtervalue": "",
		"font": 1,
		"fontsize": 10,
		"fontstyle": "kPlain",
		"gridlinescolor": "kColorDefault",
		"gridlinesdotted": false,
		"gridlinesvisible": true,
		"hasfilterarea": false,
		"hasheader": false,
		"hcell": 0,
		"headertext": "",
		"hidecolumnheader": false,
		"hideselection": false,
		"hiliteline": false,
		"linestyle": 1,
		"multipleselect": false,
		"numberformat": "",
		"objlink": 196612,
		"pagesize": 0,
		"preventlayoutanimation": false,
		"selectedlinecolor": "kColorDefault",
		"selectedlinetextcolor": "kColorDefault",
		"setlineheight": false,
		"sortascending": true,
		"sortcol": 0,
		"textcolor": "kColorDefault",
		"tooltip": "",
		"userdefined": true,
		"userinfo": "",
		"vcell": 0,
		"visible": true
	},
	"multivalueproperties": {
		"selected": 1,
		"properties": [
			{
				"columnallownulldateinput": false,
				"columnbackalpha": 255,
				"columnbackcolor": "kColorDefault",
				"columncanresize": true,
				"columncansort": true,
				"columndatacol": "CF_TITLE_CODE",
				"columndateformat": "kJSFormatNone",
				"columndateformatcustom": "",
				"columnenabled": true,
				"columnfontstyle": "kPlain",
				"columnjst": "kLeftJst",
				"columnminwidth": 0,
				"columnmode": "kJSDataGridModeAuto",
				"columnname": "Conference",
				"columnnumberformat": "",
				"columnpicklist": "",
				"columnpopuptext": false,
				"columnstyledtext": false,
				"columntextcolor": "kColorDefault",
				"columnwidth": 100
			},
			{
				"columnallownulldateinput": false,
				"columnbackalpha": 255,
				"columnbackcolor": "kColorDefault",
				"columncanresize": true,
				"columncansort": true,
				"columndatacol": "TPC_TITLE",
				"columndateformat": "kJSFormatNone",
				"columndateformatcustom": "",
				"columnenabled": true,
				"columnfontstyle": "kPlain",
				"columnjst": "kLeftJst",
				"columnminwidth": 0,
				"columnmode": "kJSDataGridModeAuto",
				"columnname": "Title",
				"columnnumberformat": "",
				"columnpicklist": "",
				"columnpopuptext": false,
				"columnstyledtext": false,
				"columntextcolor": "kColorDefault",
				"columnwidth": 371
			},
			{
				"columnallownulldateinput": false,
				"columnbackalpha": 255,
				"columnbackcolor": "kColorDefault",
				"columncanresize": true,
				"columncansort": true,
				"columndatacol": "attended",
				"columndateformat": "kJSFormatNone",
				"columndateformatcustom": "",
				"columnenabled": true,
				"columnfontstyle": "kPlain",
				"columnjst": "kLeftJst",
				"columnminwidth": 0,
				"columnmode": "kJSDataGridModeAuto",
				"columnname": "attended",
				"columnnumberformat": "",
				"columnpicklist": "",
				"columnpopuptext": false,
				"columnstyledtext": false,
				"columntextcolor": "kColorDefault",
				"columnwidth": 74
			},
			{
				"columnallownulldateinput": false,
				"columnbackalpha": 255,
				"columnbackcolor": "kColorDefault",
				"columncanresize": true,
				"columncansort": true,
				"columndatacol": "ARR_MAX_BOOKINGS",
				"columndateformat": "kJSFormatNone",
				"columndateformatcustom": "",
				"columnenabled": true,
				"columnfontstyle": "kPlain",
				"columnjst": "kLeftJst",
				"columnminwidth": 0,
				"columnmode": "kJSDataGridModeAuto",
				"columnname": "maximum",
				"columnnumberformat": "",
				"columnpicklist": "",
				"columnpopuptext": false,
				"columnstyledtext": false,
				"columntextcolor": "kColorDefault",
				"columnwidth": 80
			},
			{
				"columnallownulldateinput": false,
				"columnbackalpha": 255,
				"columnbackcolor": "kColorDefault",
				"columncanresize": true,
				"columncansort": true,
				"columndatacol": "percent",
				"columndateformat": "kJSFormatNone",
				"columndateformatcustom": "",
				"columnenabled": true,
				"columnfontstyle": "kPlain",
				"columnjst": "kLeftJst",
				"columnminwidth": 0,
				"columnmode": "kJSDataGridModeAuto",
				"columnname": "percent",
				"columnnumberformat": "",
				"columnpicklist": "",
				"columnpopuptext": false,
				"columnstyledtext": false,
				"columntextcolor": "kColorDefault",
				"columnwidth": 100
			}
		]
	},
	"layout": {
		"320": {
			"left": 0,
			"top": 8,
			"width": 560,
			"height": 312,
			"dragborder": false,
			"edgefloat": "kEFnone",
			"errortextpos": "kJSErrorTextPosUnder",
			"visible": true
		},
		"375": {
			"left": 0,
			"top": 8,
			"width": 560,
			"height": 312,
			"dragborder": false,
			"edgefloat": "kEFnone",
			"errortextpos": "kJSErrorTextPosUnder",
			"visible": true
		},
		"480": {
			"left": 0,
			"top": 8,
			"width": 560,
			"height": 312,
			"dragborder": false,
			"edgefloat": "kEFnone",
			"errortextpos": "kJSErrorTextPosUnder",
			"visible": true
		},
		"667": {
			"left": 0,
			"top": 8,
			"width": 560,
			"height": 312,
			"dragborder": false,
			"edgefloat": "kEFnone",
			"errortextpos": "kJSErrorTextPosUnder",
			"visible": true
		},
		"768": {
			"left": 0,
			"top": 8,
			"width": 560,
			"height": 312,
			"dragborder": false,
			"edgefloat": "kEFnone",
			"errortextpos": "kJSErrorTextPosUnder",
			"visible": true
		},
		"1024": {
			"left": 16,
			"top": 12,
			"width": 704,
			"height": 312,
			"dragborder": false,
			"edgefloat": "kEFnone",
			"errortextpos": "kJSErrorTextPosUnder",
			"visible": true
		},
		"1280": {
			"left": 16,
			"top": 12,
			"width": 704,
			"height": 312,
			"dragborder": false,
			"edgefloat": "kEFnone",
			"errortextpos": "kJSErrorTextPosUnder",
			"visible": true
		}
	}
}
