{
	"classtype": "kObjectclass",
	"internalversion": 5,
	"superclass": ".OWEB.Web Worker Objects\\SMTPClientWorker",
	"designtaskname": "Startup_Task",
	"cvardefs": [

	],
	"ivardefs": [
		{
			"name": "ibDebugLog",
			"order": 22,
			"type": "kBoolean",
			"subtype": 0,
			"sublen": 0
		},
		{
			"name": "ibServerPrepared",
			"order": 8,
			"type": "kBoolean",
			"subtype": 0,
			"sublen": 0,
			"initval": "kFalse"
		},
		{
			"name": "icCallbackMethod",
			"order": 25,
			"type": "kCharacter",
			"subtype": "kSimplechar",
			"sublen": 100
		},
		{
			"name": "icCompletionMessage",
			"order": 23,
			"type": "kCharacter",
			"subtype": "kSimplechar",
			"sublen": 1000
		},
		{
			"name": "icEmailBCC",
			"order": 17,
			"type": "kCharacter",
			"subtype": "kSimplechar",
			"sublen": 1000
		},
		{
			"name": "icEmailCC",
			"order": 16,
			"type": "kCharacter",
			"subtype": "kSimplechar",
			"sublen": 1000
		},
		{
			"name": "icEmailTO",
			"order": 1,
			"type": "kCharacter",
			"subtype": "kSimplechar",
			"sublen": 1000
		},
		{
			"name": "icFrom",
			"order": 14,
			"type": "kCharacter",
			"subtype": "kSimplechar",
			"sublen": 255
		},
		{
			"name": "icFromName",
			"order": 26,
			"type": "kCharacter",
			"subtype": "kSimplechar",
			"sublen": 100
		},
		{
			"name": "icNTLMdomain",
			"order": 7,
			"type": "kCharacter",
			"subtype": "kSimplechar",
			"sublen": 255
		},
		{
			"name": "icOAUTH2authCode",
			"order": 6,
			"type": "kCharacter",
			"subtype": "kSimplechar",
			"sublen": 100
		},
		{
			"name": "icPassword",
			"order": 5,
			"type": "kCharacter",
			"subtype": "kSimplechar",
			"sublen": 255
		},
		{
			"name": "icRealm",
			"order": 3,
			"type": "kCharacter",
			"subtype": "kSimplechar",
			"sublen": 255
		},
		{
			"name": "icSMTPserver",
			"order": 2,
			"type": "kCharacter",
			"subtype": "kSimplechar",
			"sublen": 255
		},
		{
			"name": "icUser",
			"order": 4,
			"type": "kCharacter",
			"subtype": "kSimplechar",
			"sublen": 255
		},
		{
			"name": "icValidationMessage",
			"order": 11,
			"type": "kCharacter",
			"subtype": "kSimplechar",
			"sublen": 255
		},
		{
			"name": "ilHeaders",
			"order": 13,
			"type": "kList",
			"subtype": "",
			"sublen": 0
		},
		{
			"name": "ilMessageParts",
			"order": 18,
			"type": "kList",
			"subtype": "",
			"sublen": 0
		},
		{
			"name": "ilProperties",
			"order": 20,
			"type": "kList",
			"subtype": "",
			"sublen": 0
		},
		{
			"name": "inAuthType",
			"order": 10,
			"type": "kInteger",
			"subtype": "kShortint",
			"sublen": 0
		},
		{
			"name": "inMessageId",
			"order": 15,
			"type": "kInteger",
			"subtype": "k64bitint",
			"sublen": 0
		},
		{
			"name": "inSecure",
			"order": 9,
			"type": "kInteger",
			"subtype": "kShortint",
			"sublen": 0
		},
		{
			"name": "inValidationCode",
			"order": 19,
			"type": "kInteger",
			"subtype": "k32bitint",
			"sublen": 0
		},
		{
			"name": "ioErrorCodes",
			"order": 21,
			"type": "kObject",
			"subtype": "infra.oErrorsWeb",
			"sublen": 0
		},
		{
			"name": "ioMessage",
			"order": 12,
			"type": "kObject",
			"subtype": ".OWEB.EMAILMessage",
			"sublen": 0
		},
		{
			"name": "irefCallbackObject",
			"order": 24,
			"type": "kItemref",
			"subtype": "",
			"sublen": 0
		}
	],
	"properties": {
		"collectperformancedata": false,
		"componenticon": 0,
		"componenttype": "kCompStoreHidden",
		"createdate": "2017-10-30 11:44:09",
		"desc": "",
		"editor": "",
		"editordata": "",
		"external": true,
		"issupercomponent": false,
		"moddate": "2018-12-04 08:19:27",
		"selfcontained": false,
		"showascheckedout": false,
		"userinfo": "",
		"version": "2"
	}
}
